utility/__init__.py
utility/file_io.py
utility/misc.py
utility/utility.py
utility/tests/__init__.py
utility/tests/test_file_io.py
utility/tests/test_misc.py
rol1510_utility-0.2.2.dist-info/LICENSE
rol1510_utility-0.2.2.dist-info/METADATA
rol1510_utility-0.2.2.dist-info/WHEEL
rol1510_utility-0.2.2.dist-info/top_level.txt
rol1510_utility-0.2.2.dist-info/RECORD
