Metadata-Version: 2.1
Name: rol1510-utility
Version: 0.2.2
Summary: Usefull stuff for simple helper scripts
Home-page: https://github.com/rol1510/utility
Author: Roland Strasser
Author-email: roland1510s@gmail.com
License: UNKNOWN
Platform: UNKNOWN
Classifier: Programming Language :: Python :: 3
Classifier: License :: OSI Approved :: MIT License
Requires-Python: >=3.6
